image_slide/__init__.py
image_slide/viewer.py
image_slide-1.0.1.dist-info/licenses/LICENSE
image_slide-1.0.1.dist-info/METADATA
image_slide-1.0.1.dist-info/WHEEL
image_slide-1.0.1.dist-info/top_level.txt
image_slide-1.0.1.dist-info/RECORD
