Metadata-Version: 2.4
Name: image-slide
Version: 1.0.1
Summary: An interactive image viewer for multidimensional numpy arrays
Author-email: Martin Buehrer <martin.buehrer@gyrotools.com>
Maintainer-email: Martin Buehrer <martin.buehrer@gyrotools.com>
License: MIT
Project-URL: Homepage, https://github.com/GyroTools/image-slide
Project-URL: Documentation, https://github.com/GyroTools/image-slide#readme
Project-URL: Repository, https://github.com/GyroTools/image-slide
Project-URL: Bug Tracker, https://github.com/GyroTools/image-slide/issues
Keywords: image,viewer,numpy,matplotlib,scientific,visualization
Classifier: Development Status :: 4 - Beta
Classifier: Intended Audience :: Science/Research
Classifier: Intended Audience :: Developers
Classifier: License :: OSI Approved :: MIT License
Classifier: Operating System :: OS Independent
Classifier: Programming Language :: Python :: 3
Classifier: Programming Language :: Python :: 3.8
Classifier: Programming Language :: Python :: 3.9
Classifier: Programming Language :: Python :: 3.10
Classifier: Programming Language :: Python :: 3.11
Classifier: Programming Language :: Python :: 3.12
Classifier: Topic :: Scientific/Engineering :: Visualization
Classifier: Topic :: Software Development :: Libraries :: Python Modules
Classifier: Topic :: Multimedia :: Graphics :: Viewers
Requires-Python: >=3.8
License-File: LICENSE
Requires-Dist: numpy>=1.19.0
Requires-Dist: matplotlib>=3.3.0
Provides-Extra: dev
Requires-Dist: pytest>=6.0; extra == "dev"
Requires-Dist: black; extra == "dev"
Requires-Dist: flake8; extra == "dev"
Requires-Dist: mypy; extra == "dev"
Provides-Extra: examples
Requires-Dist: scipy; extra == "examples"
Requires-Dist: scikit-image; extra == "examples"
Dynamic: license-file
